ppbt/__init__.py
ppbt/build.py
ppbt/common.py
ppbt/_config/aarch64/aarch64-linux-gnu-ct-ng.config
ppbt/_config/aarch64/x86_64-linux-gnu-ct-ng.config
ppbt/_config/x86_64/aarch64-linux-gnu-ct-ng.config
ppbt/_config/x86_64/x86_64-linux-gnu-ct-ng.config
ppbt/_toolchain/aarch64-linux-gnu.tar.xz
ppbt/_toolchain/aarch64-linux-gnu.tar.xz.record
ppbt-0.1.8.dist-info/LICENSE.md
ppbt-0.1.8.dist-info/METADATA
ppbt-0.1.8.dist-info/WHEEL
ppbt-0.1.8.dist-info/top_level.txt
ppbt-0.1.8.dist-info/RECORD
